CHANGES.txt
LICENSE.txt
MANIFEST.in
README.rst
setup.py
safefile/__init__.py
safefile/safefile.py
test/test_safefile.py
ujs_safefile.egg-info/PKG-INFO
ujs_safefile.egg-info/SOURCES.txt
ujs_safefile.egg-info/dependency_links.txt
ujs_safefile.egg-info/top_level.txt