Metadata-Version: 1.1
Name: ujs-safefile
Version: 0.1.0
Summary: Automated recovery file library
Home-page: http://github.com/usingjsonschema/ujs-safefile-python
Author: Joe McIntyre
Author-email: j_h_mcintyre@yahoo.com
License: MIT
Keywords: bookujs file
Platform: UNKNOWN
Classifier: Development Status :: 4 - Beta
Classifier: License :: OSI Approved :: MIT License
Classifier: Operating System :: OS Independent
Classifier: Programming Language :: Python
Classifier: Programming Language :: Python :: 2
Classifier: Programming Language :: Python :: 2.7
Classifier: Programming Language :: Python :: 3
Classifier: Programming Language :: Python :: 3.4
Classifier: Intended Audience :: Developers
Classifier: Topic :: Software Development
